deskdb/__init__.py
deskdb/db.py
deskdb-0.1.7.dist-info/LICENSE
deskdb-0.1.7.dist-info/METADATA
deskdb-0.1.7.dist-info/WHEEL
deskdb-0.1.7.dist-info/top_level.txt
deskdb-0.1.7.dist-info/RECORD
