Metadata-Version: 2.1
Name: deskdb
Version: 0.1.7
Summary: Simple yet stupid, db
Author-email: penggrin <miner.sidor@gmail.com>
License: MIT License        
Project-URL: Homepage, https://github.com/penggrin12/deskdb
Project-URL: Bug Tracker, https://github.com/penggrin12/deskdb/issues
Classifier: Programming Language :: Python :: 3
Classifier: License :: OSI Approved :: MIT License
Classifier: Operating System :: OS Independent
Requires-Python: >=3.8
License-File: LICENSE
